MANIFEST.in
README.rst
customers.json
setup.py
guest_list/__init__.py
guest_list/guest_list.py
guest_list.egg-info/PKG-INFO
guest_list.egg-info/SOURCES.txt
guest_list.egg-info/dependency_links.txt
guest_list.egg-info/not-zip-safe
guest_list.egg-info/requires.txt
guest_list.egg-info/top_level.txt