Metadata-Version: 1.0
Name: guest-list
Version: 0.1
Summary: Simple python package for a company to generate a guest list from a data file containing json encoded customer coordinates, based on their distance to the companies office.
Home-page: https://github.com/kujosHeist/guest_list
Author: Shane Carty
Author-email: shane.carty@hotmail.com
License: MIT
Platform: UNKNOWN
